{
 "action": "Create Entry",
 "action_label": "Create",
 "creation": "2026-04-20 00:31:40.432891",
 "description": "Create or review your first **CRM Interaction Log** record from this workspace.",
 "docstatus": 0,
 "doctype": "Onboarding Step",
 "idx": 0,
 "is_complete": 0,
 "is_single": 0,
 "is_skipped": 0,
 "modified": "2026-04-21 16:46:12.261326",
 "modified_by": "Administrator",
 "name": "ERPGENEX-WS-crm-03-crm_interaction_log",
 "owner": "Administrator",
 "reference_document": "CRM Interaction Log",
 "show_form_tour": 0,
 "show_full_form": 0,
 "title": "Get started with CRM Interaction Log",
 "validate_action": 1
}