{
 "charts": [
  {
   "chart_name": "CRM \u00b7 Status Bar",
   "label": "Status Bar"
  },
  {
   "chart_name": "CRM \u00b7 Customer Profile Mix",
   "label": "Customer Profile Mix"
  },
  {
   "chart_name": "CRM \u00b7 CRM Opportunity Mix",
   "label": "CRM Opportunity Mix"
  }
 ],
 "content": "[{\"id\":\"crm-h\",\"type\":\"header\",\"data\":{\"text\":\"<span class=\\\"h4\\\"><b>CRM</b></span>\",\"col\":12}},{\"id\":\"crm-nc0\",\"type\":\"number_card\",\"data\":{\"number_card_name\":\"Customer Profile\",\"col\":4}},{\"id\":\"crm-nc1\",\"type\":\"number_card\",\"data\":{\"number_card_name\":\"CRM Interaction Log\",\"col\":4}},{\"id\":\"crm-nc2\",\"type\":\"number_card\",\"data\":{\"number_card_name\":\"CRM Lead\",\"col\":4}},{\"id\":\"crm-nc3\",\"type\":\"number_card\",\"data\":{\"number_card_name\":\"CRM Opportunity\",\"col\":4}},{\"id\":\"crm-nc4\",\"type\":\"number_card\",\"data\":{\"number_card_name\":\"CRM Case Ticket\",\"col\":4}},{\"id\":\"crm-nc5\",\"type\":\"number_card\",\"data\":{\"number_card_name\":\"CRM Campaign\",\"col\":4}},{\"id\":\"crm-ch0\",\"type\":\"chart\",\"data\":{\"chart_name\":\"Status Bar\",\"col\":4}},{\"id\":\"crm-ch1\",\"type\":\"chart\",\"data\":{\"chart_name\":\"Customer Profile Mix\",\"col\":4}},{\"id\":\"crm-ch2\",\"type\":\"chart\",\"data\":{\"chart_name\":\"CRM Opportunity Mix\",\"col\":4}},{\"id\":\"crm-ops\",\"type\":\"header\",\"data\":{\"text\":\"<b>Quick Actions</b>\",\"col\":12}},{\"id\":\"crm-sc0\",\"type\":\"shortcut\",\"data\":{\"shortcut_name\":\"Customer Profile\",\"col\":3}},{\"id\":\"crm-sc1\",\"type\":\"shortcut\",\"data\":{\"shortcut_name\":\"CRM Interaction Log\",\"col\":3}},{\"id\":\"crm-sc2\",\"type\":\"shortcut\",\"data\":{\"shortcut_name\":\"CRM Lead\",\"col\":3}},{\"id\":\"crm-sc3\",\"type\":\"shortcut\",\"data\":{\"shortcut_name\":\"CRM Opportunity\",\"col\":3}},{\"id\":\"crm-sc4\",\"type\":\"shortcut\",\"data\":{\"shortcut_name\":\"CRM Case Ticket\",\"col\":3}},{\"id\":\"crm-sc5\",\"type\":\"shortcut\",\"data\":{\"shortcut_name\":\"CRM Campaign\",\"col\":3}},{\"id\":\"crm-sc6\",\"type\":\"shortcut\",\"data\":{\"shortcut_name\":\"CRM Pipeline Value\",\"col\":3}},{\"id\":\"crm-sc7\",\"type\":\"shortcut\",\"data\":{\"shortcut_name\":\"CRM Case SLA Compliance\",\"col\":3}},{\"id\":\"crm-sc8\",\"type\":\"shortcut\",\"data\":{\"shortcut_name\":\"CRM Customer Revenue\",\"col\":3}}]",
 "creation": "2026-04-15 12:28:24.982364",
 "custom_blocks": [],
 "docstatus": 0,
 "doctype": "Workspace",
 "for_user": "",
 "hide_custom": 0,
 "icon": "customer",
 "idx": 0,
 "is_hidden": 0,
 "label": "CRM",
 "links": [
  {
   "hidden": 0,
   "is_query_report": 0,
   "label": "Customer 360",
   "link_count": 0,
   "onboard": 0,
   "type": "Card Break"
  },
  {
   "hidden": 0,
   "is_query_report": 0,
   "label": "Customer Profile",
   "link_count": 0,
   "link_to": "Customer Profile",
   "link_type": "DocType",
   "onboard": 0,
   "type": "Link"
  },
  {
   "hidden": 0,
   "is_query_report": 0,
   "label": "CRM Interaction Log",
   "link_count": 0,
   "link_to": "CRM Interaction Log",
   "link_type": "DocType",
   "onboard": 0,
   "type": "Link"
  },
  {
   "hidden": 0,
   "is_query_report": 0,
   "label": "Pipeline",
   "link_count": 0,
   "onboard": 0,
   "type": "Card Break"
  },
  {
   "hidden": 0,
   "is_query_report": 0,
   "label": "CRM Lead",
   "link_count": 0,
   "link_to": "CRM Lead",
   "link_type": "DocType",
   "onboard": 0,
   "type": "Link"
  },
  {
   "hidden": 0,
   "is_query_report": 0,
   "label": "CRM Opportunity",
   "link_count": 0,
   "link_to": "CRM Opportunity",
   "link_type": "DocType",
   "onboard": 0,
   "type": "Link"
  },
  {
   "hidden": 0,
   "is_query_report": 0,
   "label": "Service & Marketing",
   "link_count": 0,
   "onboard": 0,
   "type": "Card Break"
  },
  {
   "hidden": 0,
   "is_query_report": 0,
   "label": "CRM Case Ticket",
   "link_count": 0,
   "link_to": "CRM Case Ticket",
   "link_type": "DocType",
   "onboard": 0,
   "type": "Link"
  },
  {
   "hidden": 0,
   "is_query_report": 0,
   "label": "CRM Campaign",
   "link_count": 0,
   "link_to": "CRM Campaign",
   "link_type": "DocType",
   "onboard": 0,
   "type": "Link"
  },
  {
   "hidden": 0,
   "is_query_report": 0,
   "label": "Reports",
   "link_count": 0,
   "onboard": 0,
   "type": "Card Break"
  },
  {
   "hidden": 0,
   "is_query_report": 1,
   "label": "CRM Pipeline Value",
   "link_count": 0,
   "link_to": "CRM Pipeline Value",
   "link_type": "Report",
   "onboard": 0,
   "type": "Link"
  },
  {
   "hidden": 0,
   "is_query_report": 1,
   "label": "CRM Case SLA Compliance",
   "link_count": 0,
   "link_to": "CRM Case SLA Compliance",
   "link_type": "Report",
   "onboard": 0,
   "type": "Link"
  },
  {
   "hidden": 0,
   "is_query_report": 1,
   "label": "CRM Customer Revenue",
   "link_count": 0,
   "link_to": "CRM Customer Revenue",
   "link_type": "Report",
   "onboard": 0,
   "type": "Link"
  }
 ],
 "modified": "2026-04-17 23:45:48.134265",
 "modified_by": "Administrator",
 "module": "Omnexa Customer Core",
 "name": "CRM",
 "number_cards": [
  {
   "label": "Customer Profile",
   "number_card_name": "Customer Profile"
  },
  {
   "label": "CRM Interaction Log",
   "number_card_name": "CRM Interaction Log"
  },
  {
   "label": "CRM Lead",
   "number_card_name": "CRM Lead"
  },
  {
   "label": "CRM Opportunity",
   "number_card_name": "CRM Opportunity"
  },
  {
   "label": "CRM Case Ticket",
   "number_card_name": "CRM Case Ticket"
  },
  {
   "label": "CRM Campaign",
   "number_card_name": "CRM Campaign"
  }
 ],
 "owner": "Administrator",
 "parent_page": "",
 "public": 1,
 "quick_lists": [],
 "restrict_to_domain": "",
 "roles": [],
 "sequence_id": 8.2,
 "shortcuts": [
  {
   "color": "Cyan",
   "doc_view": "List",
   "label": "Customer Profile",
   "link_to": "Customer Profile",
   "type": "DocType"
  },
  {
   "color": "Blue",
   "doc_view": "List",
   "label": "CRM Interaction Log",
   "link_to": "CRM Interaction Log",
   "type": "DocType"
  },
  {
   "color": "Purple",
   "doc_view": "List",
   "label": "CRM Lead",
   "link_to": "CRM Lead",
   "type": "DocType"
  },
  {
   "color": "Orange",
   "doc_view": "List",
   "label": "CRM Opportunity",
   "link_to": "CRM Opportunity",
   "type": "DocType"
  },
  {
   "color": "Green",
   "doc_view": "List",
   "label": "CRM Case Ticket",
   "link_to": "CRM Case Ticket",
   "type": "DocType"
  },
  {
   "color": "Red",
   "doc_view": "List",
   "label": "CRM Campaign",
   "link_to": "CRM Campaign",
   "type": "DocType"
  },
  {
   "color": "Teal",
   "doc_view": "",
   "label": "CRM Pipeline Value",
   "link_to": "CRM Pipeline Value",
   "report_ref_doctype": "CRM Opportunity",
   "type": "Report"
  },
  {
   "color": "Pink",
   "doc_view": "",
   "label": "CRM Case SLA Compliance",
   "link_to": "CRM Case SLA Compliance",
   "report_ref_doctype": "CRM Case Ticket",
   "type": "Report"
  },
  {
   "color": "Cyan",
   "doc_view": "",
   "label": "CRM Customer Revenue",
   "link_to": "CRM Customer Revenue",
   "report_ref_doctype": "Customer Profile",
   "type": "Report"
  }
 ],
 "title": "CRM"
}